owid/grapher/__init__.py
owid/grapher/export.py
owid/grapher/grapher_state.py
owid/grapher/notebook.py
owid/grapher/utils.py
owid_grapher_py-0.3.1.dist-info/METADATA
owid_grapher_py-0.3.1.dist-info/WHEEL
owid_grapher_py-0.3.1.dist-info/RECORD
