Metadata-Version: 2.4
Name: owid-grapher-py
Version: 0.3.1
Summary: OWID charts for rendering in Jupyter notebooks.
Project-URL: Homepage, https://github.com/owid/owid-grapher-py
Project-URL: Repository, https://github.com/owid/owid-grapher-py
Project-URL: Documentation, https://github.com/owid/owid-grapher-py#readme
Project-URL: Bug Tracker, https://github.com/owid/owid-grapher-py/issues
Author-email: Lars Yencken <lars@yencken.org>, Mojmir Vinkler <mojmir@ourworldindata.org>
License: MIT
Keywords: charts,data-visualization,graphs,jupyter,ourworldindata,owid
Classifier: Development Status :: 4 - Beta
Classifier: Framework :: Jupyter
Classifier: Intended Audience :: Developers
Classifier: Intended Audience :: Science/Research
Classifier: License :: OSI Approved :: MIT License
Classifier: Programming Language :: Python :: 3
Classifier: Programming Language :: Python :: 3.10
Classifier: Programming Language :: Python :: 3.11
Classifier: Programming Language :: Python :: 3.12
Classifier: Topic :: Scientific/Engineering :: Visualization
Requires-Python: >=3.10
Requires-Dist: click>=8.0.0
Requires-Dist: dataclasses-json>=0.6.7
Requires-Dist: jsonschema>=3.2.0
Requires-Dist: pandas>=2.2.3
Requires-Dist: python-dateutil>=2.8.1
Requires-Dist: requests>=2.26.0
